[
  {
    "topic": "One-Pan Lemon Butter Garlic Salmon",
    "title": "One-Pan Lemon Butter Garlic Salmon: A Game-Changing Recipe",
    "published_at": "2026-07-15T05:42:43.874706",
    "blogger": {
      "success": true,
      "url": "https://dailytastyrecipes99.blogspot.com/2026/07/one-pan-lemon-butter-garlic-salmon-game_0747110595.html",
      "post_id": "3584369725339134494"
    },
    "pinterest": {
      "success": true,
      "pin_url": "Handled by Make.com",
      "pin_id": ""
    },
    "keywords": [
      "One-Pan Salmon",
      "Lemon Butter Garlic",
      "Salmon Recipes",
      "Easy Dinner Ideas",
      "Healthy Meals"
    ],
    "word_count": 461
  }
]